{
  "version": "1.1.1",
  "windows": {
    "main": {
      "main": true,
      "url": "app://editor/index.html",
      "windowType": "dockable",
      "x": -1835,
      "y": 23,
      "width": 1835,
      "height": 1057,
      "layout": {
        "children": [
          {
            "children": [
              {
                "active": 0,
                "children": [
                  "hierarchy"
                ],
                "height": 459.109375,
                "type": "panel",
                "width": 308
              },
              {
                "active": 0,
                "children": [
                  "assets"
                ],
                "height": 512.109375,
                "type": "panel",
                "width": 308
              }
            ],
            "height": 973.21875,
            "type": "dock-v",
            "width": 308
          },
          {
            "children": [
              {
                "active": 0,
                "children": [
                  "scene"
                ],
                "height": 651.140625,
                "type": "panel",
                "width": 1088
              },
              {
                "active": 0,
                "children": [
                  "console",
                  "timeline"
                ],
                "height": 320.0625,
                "type": "panel",
                "width": 1088
              }
            ],
            "height": 973.21875,
            "type": "dock-v",
            "width": 1088
          },
          {
            "active": 0,
            "children": [
              "inspector"
            ],
            "height": 973.21875,
            "type": "panel",
            "width": 435
          }
        ],
        "type": "dock-h"
      },
      "panels": [
        "hierarchy",
        "assets",
        "console",
        "timeline",
        "inspector",
        "scene"
      ]
    }
  },
  "panels": {
    "simulator-debugger": {
      "x": 695,
      "y": 220,
      "width": 800,
      "height": 622
    },
    "builder": {
      "x": -954,
      "y": 199,
      "width": 654,
      "height": 722
    }
  }
}